{"id": 1018, "fda_submission_number": "K211279", "device_name": "Volpara Imaging Software", "company": "Volpara Health Technologies Limited", "decision_date": "2021-07-27", "specialty_panel": "Radiology", "product_code": "LLZ", "device_class": "2", "clinical_use_case": "Image Processing & Enhancement", "claim_category": "quantification", "validation_design": "bench_only", "sensitivity": null, "specificity": null, "auc": null, "sample_size": null, "num_sites": null, "intended_use": "Volpara Imaging Software is a software application intended for use with the raw data from digital breast x-ray systems, including tomosynthesis. Volpara Imaging Software calculates and quantifies a d", "autonomous_or_assistive": "assistive", "is_concern_zone": false, "safety_event_count": 0, "recall_count": 0, "has_fda_summary": true, "fda_summary_url": "https://www.accessdata.fda.gov/cdrh_docs/pdf21/K211279.pdf", "years_since_clearance": 4.8, "clearance_year": "2021", "clearance_details": {"device_class": "2", "clearance_type": "Special", "decision_code": "SESE", "statement_or_summary": "Summary", "summary_url": "https://www.accessdata.fda.gov/cdrh_docs/pdf21/K211279.pdf", "date_received": "2021-04-27", "expedited_review": false, "third_party_review": false}, "intended_use_full": "Volpara Imaging Software is a software application intended for use with the raw data from digital breast x-ray systems, including tomosynthesis. Volpara Imaging Software calculates and quantifies a density map and from that determines volumetric breast density as a ratio of fibroglandular tissue and total breast volume estimates. Volpara Imaging Software provides these numerical values along with a BI-RADS breast density 4th or 5th Edition category and quality assurance metrics (i.e., dose and pressure) to aid healthcare professionals in the assessment of breast composition. Volpara Imaging Software is not a diagnostic aid and should be used only as adjunctive information when the final assessment of breast density category is made by an MQSA-qualified interpreting physician.", "target_condition": "Breast density assessment and breast composition evaluation", "ground_truth": null, "other_metrics": null, "safety_events": [], "recalls": []}