{"id": 1303, "fda_submission_number": "K182034", "device_name": "Arterys MICA", "company": "Arterys Inc.", "decision_date": "2018-10-17", "specialty_panel": "Radiology", "product_code": "LLZ", "device_class": "2", "clinical_use_case": "Image Processing & Enhancement", "claim_category": "quantification", "validation_design": "bench_only", "sensitivity": null, "specificity": null, "auc": null, "sample_size": null, "num_sites": null, "intended_use": "Arterys MICA software is a medical diagnostic application that displays, processes, stores, and transfers DICOM and non-DICOM medical data, with the exception of mammography. It provides the capabilit", "autonomous_or_assistive": "assistive", "is_concern_zone": false, "safety_event_count": 0, "recall_count": 0, "has_fda_summary": true, "fda_summary_url": "https://www.accessdata.fda.gov/cdrh_docs/pdf18/K182034.pdf", "years_since_clearance": 7.5, "clearance_year": "2018", "clearance_details": {"device_class": "2", "clearance_type": "Traditional", "decision_code": "SESE", "statement_or_summary": "Summary", "summary_url": "https://www.accessdata.fda.gov/cdrh_docs/pdf18/K182034.pdf", "date_received": "2018-07-30", "expedited_review": false, "third_party_review": false}, "intended_use_full": "Arterys MICA software is a medical diagnostic application that displays, processes, stores, and transfers DICOM and non-DICOM medical data, with the exception of mammography. It provides the capability to store images and patient information, and perform filtering, digital manipulation, and quantitative measurements. The client software is designed to run on standard personal and business computers. Arterys MICA includes an optional Cardio AI module which is used to analyze the heart and its major vessels using multi-slice, multi-phase, and velocity-encoded cardiovascular magnetic resonance (MR) images. It provides clinically relevant and reproducible, quantitative data, and has been tested and validated on MR images acquired from both 1.5T and 3.0 T MR Scanners. Arterys MICA includes an optional Oncology AI module which provides analytical tools to help the user assess and document changes in morphological activity at diagnostic and therapy follow-up examinations. It is a tool used to support the oncological workflow by helping the user confirm the absence or presence of lesions, including evaluation, quantification, follow-up, and documentation of any such lesions. Arterys MICA software is intended to be used as a support tool by trained healthcare professionals to aid in diagnosis. It is intended to provide image and related information that is interpreted by a trained professional to render findings and/or diagnosis, but it does not directly generate any diagnosis or potential findings.", "target_condition": "Cardiac and oncologic imaging assessment, including cardiac function analysis and lesion evaluation/tracking", "ground_truth": null, "other_metrics": null, "safety_events": [], "recalls": []}