{"id": 1418, "fda_submission_number": "K081140", "device_name": "VISENSIA", "company": "OBS MEDICAL", "decision_date": "2008-07-17", "specialty_panel": "Cardiovascular", "product_code": "MHX", "device_class": "2", "clinical_use_case": "Cardiac Diagnostics", "trust_level": "moderate", "evidence_score": 50, "evidence_count": 6, "evidence_direct": 6, "evidence_company": 0, "evidence_count_ss": 0, "evidence_count_oa": 0, "evidence_total": 6, "has_regulatory_data": false, "has_family_evidence": false, "has_denovo_summary": false, "any_evidence": true, "safety_event_count": 0, "recall_count": 0, "trial_count": 0, "has_fda_summary": true, "fda_summary_url": "https://www.accessdata.fda.gov/cdrh_docs/pdf08/K081140.pdf", "years_since_clearance": 17.8, "clearance_year": "2008", "score_breakdown": {"total": 50, "trust_level": "moderate", "evidence_volume": 35, "study_quality": 15, "safety": 0, "trials": 0, "detail": {"n_direct_publications": 5.5, "n_company_publications": 0.5, "n_publications": 6, "n_safety_events": 0, "n_deaths": 0, "n_injuries": 0, "n_recalls": 0, "n_trials": 0, "n_trials_with_results": 0}}, "clearance_details": {"device_class": "2", "clearance_type": "Traditional", "decision_code": "SESE", "statement_or_summary": "Summary", "summary_url": "https://www.accessdata.fda.gov/cdrh_docs/pdf08/K081140.pdf", "date_received": "2008-04-22", "expedited_review": false, "third_party_review": false}, "evidence": [{"pmid": "41780973", "title": "Predictive accuracy of Early Warning Score Systems for Detecting Critically Ill Patients in an Outpatient Setting.", "journal": "Internal medicine (Tokyo, Japan)", "pub_date": "2026 Mar 3", "study_type": "other", "match_tier": "direct", "relevance": "relevant"}, {"pmid": "40742731", "title": "Assessing Clinical Impressions of Early Warning Score Integration With the Rapid Response Team: Protocol for a Prospective Cohort Study.", "journal": "JMIR research protocols", "pub_date": "2025 Jul 31", "study_type": "clinical_study", "match_tier": "direct", "relevance": "relevant"}, {"pmid": "37246915", "title": "Prospective Evaluation of a Dynamic Acuity Score for Regularly Assessing a Critically Ill Patient's Risk of Mortality.", "journal": "Critical care medicine", "pub_date": "2023 Oct 1", "study_type": "clinical_study", "match_tier": "direct", "relevance": "maybe"}, {"pmid": "37154986", "title": "Comparing Continuous with Periodic Vital Sign Scoring for Clinical Deterioration Using a Patient Data Model.", "journal": "Journal of medical systems", "pub_date": "2023 May 8", "study_type": "other", "match_tier": "direct", "relevance": "relevant"}, {"pmid": "33530838", "title": "Can Early Warning Systems Enhance Detection of High Risk Patients by Rapid Response Teams?", "journal": "Journal of intensive care medicine", "pub_date": "2021 May", "study_type": "other", "match_tier": "direct", "relevance": "relevant"}, {"pmid": "19963616", "title": "Telemetry-based vital sign monitoring for ambulatory hospital patients.", "journal": "Annual International Conference of the IEEE Engineering in Medicine and Biology Society. IEEE Engineering in Medicine and Biology Society. Annual International Conference", "pub_date": "2009", "study_type": "other", "match_tier": "direct", "relevance": "relevant"}], "evidence_semantic_scholar": [], "evidence_openalex": [], "regulatory_evidence": {}, "family_evidence": {}, "denovo_summary": {}, "safety_events": [], "recalls": [], "trials": []}