{"id": 181, "fda_submission_number": "K243810", "device_name": "TraumaCad Neo (1.1)", "company": "Brainlab Ltd.", "decision_date": "2025-06-04", "specialty_panel": "Radiology", "product_code": "QIH", "device_class": "2", "clinical_use_case": "Image Processing & Enhancement", "claim_category": "quantification", "validation_design": "bench_only", "sensitivity": null, "specificity": null, "auc": null, "sample_size": 349, "num_sites": 7, "intended_use": "TraumaCad Neo is indicated for assisting healthcare professionals to analyze orthopedic conditions and to plan orthopedic procedures by overlaying on relevant radiological images visual information su", "autonomous_or_assistive": "assistive", "is_concern_zone": false, "safety_event_count": 0, "recall_count": 0, "has_fda_summary": true, "fda_summary_url": "https://www.accessdata.fda.gov/cdrh_docs/pdf24/K243810.pdf", "years_since_clearance": 0.9, "clearance_year": "2025", "clearance_details": {"device_class": "2", "clearance_type": "Traditional", "decision_code": "SESE", "statement_or_summary": "Summary", "summary_url": "https://www.accessdata.fda.gov/cdrh_docs/pdf24/K243810.pdf", "date_received": "2024-12-11", "expedited_review": false, "third_party_review": false}, "intended_use_full": "TraumaCad Neo is indicated for assisting healthcare professionals to analyze orthopedic conditions and to plan orthopedic procedures by overlaying on relevant radiological images visual information such as measurements and prosthesis templates. Clinical judgment and experience are required to properly use the software. The software is not intended for primary radiological image interpretation or radiological appraisal. Device is not intended for use on mobile phones.", "target_condition": "Orthopedic conditions requiring surgical planning and post-operative assessment, specifically total hip arthroplasty", "ground_truth": "Ground-truth annotations done by qualified and trained personnel", "other_metrics": "Implant detection accuracy: 99%; Landmark detection accuracy within 4mm: 92%", "safety_events": [], "recalls": []}